knowledge_base_search/__init__.py
knowledge_base_search/answer_generator.py
knowledge_base_search/knowledge_base.py
knowledge_base_search/logger.py
knowledge_base_search/preprocessing/__init__.py
knowledge_base_search/preprocessing/document.py
knowledge_base_search/preprocessing/text_processing.py
knowledge_base_search/search/__init__.py
knowledge_base_search/search/auto_search.py
knowledge_base_search/search/base_search_algorithm.py
knowledge_base_search/search/bert_search.py
knowledge_base_search/search/minilm_search.py
knowledge_base_search/search/mpnet_search.py
knowledge_base_search/search/tfidf_search.py
knowledge_base_search/utils/__init__.py
knowledge_base_search/utils/helpers.py
knowledge_base_search-0.1.0.dist-info/METADATA
knowledge_base_search-0.1.0.dist-info/WHEEL
knowledge_base_search-0.1.0.dist-info/top_level.txt
knowledge_base_search-0.1.0.dist-info/RECORD
