Metadata-Version: 2.1
Name: knowledge-base-search
Version: 0.1.0
Summary: A tool to search and retrieve relevant documents from a knowledge base using BERT/MiniLM embedding or a custom search implementation, then generate human-readable answers using OpenAI API.
Home-page: https://github.com/cabeywic/knowledge-base-search
Author: Charaka Abeywickrama
Author-email: charaka.abeywickrama@gmail.com
Classifier: Development Status :: 3 - Alpha
Classifier: License :: OSI Approved :: MIT License
Classifier: Programming Language :: Python :: 3
Classifier: Programming Language :: Python :: 3.6
Classifier: Programming Language :: Python :: 3.7
Classifier: Programming Language :: Python :: 3.8
Classifier: Programming Language :: Python :: 3.9
Requires-Python: >=3.6
Requires-Dist: torch
Requires-Dist: transformers
Requires-Dist: numpy
Requires-Dist: scikit-learn
Requires-Dist: spacy
Requires-Dist: nltk
Requires-Dist: python-dotenv
Requires-Dist: openai
Requires-Dist: gensim
